[
    {
        "name": " Dhamail Dance",
        "courseTeacher": "Ustad Goutam Roy",
        "duration": "12 month",
        "courseFee": 500000,
        "image": "https://www.udanceacademy.net/wp-content/uploads/2017/08/Dhamail.jpg"
    },
    {
        "name": " Baul dance",
        "courseTeacher": "Sree Susmita Pal",
        "duration": "8 month",
        "courseFee": 400000,
        "image": "https://www.udanceacademy.net/wp-content/uploads/2017/08/Baul-Dance.jpg"
    },
    {
        "name": "Dhali dance",
        "courseTeacher": "Priya Rani Roy",
        "duration": "7 month",
        "courseFee": 200000,
        "image": "https://www.udanceacademy.net/wp-content/uploads/2017/08/Dhali-dance-2.jpg"
    },
    {
        "name": "Gambhira Dance",
        "courseTeacher": "Visnu Roy",
        "duration": "2 month",
        "courseFee": 100000,
        "image": "https://www.udanceacademy.net/wp-content/uploads/2017/08/Ghambir-Dance.jpg"
    },
    {
        "name": "Ghatu dance",
        "courseTeacher": "Samantha Paul",
        "duration": "4 month",
        "courseFee": 15000,
        "image": "https://www.udanceacademy.net/wp-content/uploads/2017/08/Ghatu-dance.jpg"
    },
    {
        "name": "Jari dance",
        "courseTeacher": "Ashis Roy",
        "duration": "2 month",
        "courseFee": 5000,
        "image": "https://www.udanceacademy.net/wp-content/uploads/2017/08/Jari-dance.jpg"
    },
    {
        "name": " Khemta dance",
        "courseTeacher": "Dipok Bormon",
        "duration": "5 month",
        "courseFee": 25000,
        "image": "https://www.udanceacademy.net/wp-content/uploads/2017/08/khemta-dance.jpg"
    },
    {
        "name": "Lathi dance",
        "courseTeacher": "Lathial Soumitro",
        "duration": "1 month",
        "courseFee": 5000,
        "image": "https://www.udanceacademy.net/wp-content/uploads/2017/08/Lathi-dance.jpg"
    },
    {
        "name": "Mask dance",
        "courseTeacher": "Sukla Bormon",
        "duration": "2 month",
        "courseFee": 12000,
        "image": "https://www.udanceacademy.net/wp-content/uploads/2017/08/Musk-dance.jpg"
    },
    {
        "name": "Puppet dance",
        "courseTeacher": "Vupen Das",
        "duration": "1 month",
        "courseFee": 10000,
        "image": "https://www.udanceacademy.net/wp-content/uploads/2017/08/Puppet-dance.jpg"
    },
    {
        "name": "Tribal dance",
        "courseTeacher": "Samin Mollik",
        "duration": "3 month",
        "courseFee": 14000,
        "image": "https://www.udanceacademy.net/wp-content/uploads/2017/08/tribal.jpg"
    },
    {
        "name": "Modern dance",
        "courseTeacher": "Jack Denial",
        "duration": "3 month",
        "courseFee": 25000,
        "image": "https://www.udanceacademy.net/wp-content/uploads/2017/08/Modern-dance-768x517.png"
    },
    {
        "name": "Hip Hop",
        "courseTeacher": "Danush Choula",
        "duration": "5 month",
        "courseFee": 15000,
        "image": "https://images.unsplash.com/photo-1537365587684-f490102e1225?ixid=MnwxMjA3fDB8MHxzZWFyY2h8NXx8ZGFuY2V8ZW58MHx8MHx8&ixlib=rb-1.2.1&auto=format&fit=crop&w=500&q=60"
    }
]